formulascraper.py
formulascraper-1.2.2.dist-info/LICENSE
formulascraper-1.2.2.dist-info/METADATA
formulascraper-1.2.2.dist-info/WHEEL
formulascraper-1.2.2.dist-info/RECORD
