Metadata-Version: 2.1
Name: formulascraper
Version: 1.2.2
Summary: A Python library for parsing Formula data.
License: MIT
Author: ryazhenkofc
Author-email: ryazhenkofc@gmail.com
Requires-Python: >=3.11,<4.0
Classifier: License :: OSI Approved :: MIT License
Classifier: Programming Language :: Python :: 3
Classifier: Programming Language :: Python :: 3.11
Classifier: Programming Language :: Python :: 3.12
Requires-Dist: beautifulsoup4 (>=4.12.2,<5.0.0)
Requires-Dist: requests (>=2.31.0,<3.0.0)
